netuitive/__init__.py
netuitive/attribute.py
netuitive/check.py
netuitive/client.py
netuitive/element.py
netuitive/event.py
netuitive/metric.py
netuitive/relation.py
netuitive/sample.py
netuitive/tag.py
netuitive/util.py
netuitive-0.3.4.dist-info/METADATA
netuitive-0.3.4.dist-info/RECORD
netuitive-0.3.4.dist-info/WHEEL
netuitive-0.3.4.dist-info/top_level.txt
