Metadata-Version: 2.1
Name: netuitive
Version: 0.3.4
Summary: Python Client for Netuitive Cloud
Home-page: https://github.com/netuitive/netuitive-client-python
Author: Netuitive
Author-email: python@netuitive.com
License: Apache License 2.0
Keywords: netuitive
Platform: UNKNOWN
Classifier: Development Status :: 4 - Beta
Classifier: Intended Audience :: Developers
Classifier: License :: OSI Approved :: Apache Software License
Classifier: Topic :: Software Development :: Libraries :: Python Modules
Classifier: Natural Language :: English
Classifier: Programming Language :: Python :: 2
Classifier: Programming Language :: Python :: 2.6
Classifier: Programming Language :: Python :: 2.7
Classifier: Programming Language :: Python :: 3
Classifier: Programming Language :: Python :: 3.3
Classifier: Programming Language :: Python :: 3.4
Classifier: Programming Language :: Python :: 3.5
